dara/__init__.py
dara/bgmn_worker.py
dara/cif.py
dara/cif2str.py
dara/cli.py
dara/eflech_worker.py
dara/generate_control_file.py
dara/jobs.py
dara/peak_detection.py
dara/plot.py
dara/py.typed
dara/refine.py
dara/result.py
dara/schema.py
dara/settings.py
dara/structure_db.py
dara/utils.py
dara/xrd.py
dara/bgmn/__init__.py
dara/bgmn/download_bgmn.py
dara/data/README.md
dara/data/__init__.py
dara/data/cod_filtered_info_2024.json.gz
dara/data/common_gases.json
dara/data/icsd_filtered_info_2024.json.gz
dara/data/icsd_filtered_info_2024_v2.json.gz
dara/data/icsd_filtered_info_2025_v3.json.gz
dara/data/mp_struct_info.json.gz
dara/data/possible_species.txt
dara/data/BGMN-Templates/Devices/Aeris-fds-Pixcel1d-Medipix3.geq
dara/data/BGMN-Templates/Devices/Aeris-fds-Pixcel1d-Medipix3.ger
dara/data/BGMN-Templates/Devices/Aeris-fds-Pixcel1d-Medipix3.sav
dara/data/BGMN-Templates/Devices/Aeris-fds-Pixcel1d-Medipix3.tpl
dara/data/BGMN-Templates/Devices/D8_6Div_4SS.geq
dara/data/BGMN-Templates/Devices/D8_6Div_4SS.ger
dara/data/BGMN-Templates/Devices/D8_6Div_4SS.sav
dara/data/BGMN-Templates/Devices/D8_6Div_4SS.tpl
dara/data/BGMN-Templates/Devices/LBL-d8-LynxEyeXE.SAV
dara/data/BGMN-Templates/Devices/LBL-d8-LynxEyeXE.geq
dara/data/BGMN-Templates/Devices/LBL-d8-LynxEyeXE.ger
dara/data/BGMN-Templates/Devices/LBL-d8-LynxEyeXE.tpl
dara/data/BGMN-Templates/Devices/PW3040-FDS-ADS-Xcelerator.geq
dara/data/BGMN-Templates/Devices/PW3040-FDS-ADS-Xcelerator.ger
dara/data/BGMN-Templates/Devices/PW3040-FDS-ADS-Xcelerator.sav
dara/data/BGMN-Templates/Devices/PW3040-FDS-ADS-Xcelerator.tpl
dara/data/BGMN-Templates/Devices/RMS-D8-ADS-15-Glass-LynxEyeXE-bkgr.xy
dara/data/BGMN-Templates/Devices/RMS-D8-ADS-15-Glass-LynxEyeXE.geq
dara/data/BGMN-Templates/Devices/RMS-D8-ADS-15-Glass-LynxEyeXE.ger
dara/data/BGMN-Templates/Devices/RMS-D8-ADS-15-Glass-LynxEyeXE.sav
dara/data/BGMN-Templates/Devices/RMS-D8-ADS-15-Glass-LynxEyeXE.tpl
dara/data/BGMN-Templates/Devices/RMS-D8-ADS-15-LynxEyeXE-bkgr.xy
dara_xrd-1.1.5.dist-info/licenses/LICENSE
dara_xrd-1.1.5.dist-info/METADATA
dara_xrd-1.1.5.dist-info/WHEEL
dara_xrd-1.1.5.dist-info/entry_points.txt
dara_xrd-1.1.5.dist-info/top_level.txt
dara_xrd-1.1.5.dist-info/RECORD
